{
  "a_comp_cor_00": {
    "CumulativeVarianceExplained": 0.0838046623,
    "Mask": "CSF",
    "Method": "aCompCor",
    "Retained": true,
    "SingularValue": 69.4197616185,
    "VarianceExplained": 0.0838046623
  },
  "a_comp_cor_01": {
    "CumulativeVarianceExplained": 0.1188237355,
    "Mask": "CSF",
    "Method": "aCompCor",
    "Retained": true,
    "SingularValue": 44.8746786502,
    "VarianceExplained": 0.0350190732
  },
  "a_comp_cor_02": {
    "CumulativeVarianceExplained": 0.1485058395,
    "Mask": "CSF",
    "Method": "aCompCor",
    "Retained": true,
    "SingularValue": 41.3139166442,
    "VarianceExplained": 0.029682104
  },
  "a_comp_cor_03": {
    "CumulativeVarianceExplained": 0.1692525444,
    "Mask": "CSF",
    "Method": "aCompCor",
    "Retained": true,
    "SingularValue": 34.5401001081,
    "VarianceExplained": 0.0207467048
  },
  "a_comp_cor_04": {
    "CumulativeVarianceExplained": 0.1881510735,
    "Mask": "CSF",
    "Method": "aCompCor",
    "Retained": true,
    "SingularValue": 32.9657552375,
    "VarianceExplained": 0.0188985291
  },
  "a_comp_cor_05": {
    "CumulativeVarianceExplained": 0.2065580364,
    "Mask": "CSF",
    "Method": "aCompCor",
    "Retained": true,
    "SingularValue": 32.5341973111,
    "VarianceExplained": 0.0184069629
  },
  "a_comp_cor_06": {
    "CumulativeVarianceExplained": 0.2244173837,
    "Mask": "CSF",
    "Method": "aCompCor",
    "Retained": true,
    "SingularValue": 32.046589628,
    "VarianceExplained": 0.0178593473
  },
  "a_comp_cor_07": {
    "CumulativeVarianceExplained": 0.2420135192,
    "Mask": "CSF",
    "Method": "aCompCor",
    "Retained": true,
    "SingularValue": 31.809561071,
    "VarianceExplained": 0.0175961355
  },
  "a_comp_cor_08": {
    "CumulativeVarianceExplained": 0.2592673018,
    "Mask": "CSF",
    "Method": "aCompCor",
    "Retained": true,
    "SingularValue": 31.4985954973,
    "VarianceExplained": 0.0172537827
  },
  "a_comp_cor_09": {
    "CumulativeVarianceExplained": 0.2755395035,
    "Mask": "CSF",
    "Method": "aCompCor",
    "Retained": true,
    "SingularValue": 30.5894865451,
    "VarianceExplained": 0.0162722017
  },
  "a_comp_cor_10": {
    "CumulativeVarianceExplained": 0.2913914569,
    "Mask": "CSF",
    "Method": "aCompCor",
    "Retained": true,
    "SingularValue": 30.1918983867,
    "VarianceExplained": 0.0158519534
  },
  "a_comp_cor_100": {
    "CumulativeVarianceExplained": 0.4625877019,
    "Mask": "combined",
    "Method": "aCompCor",
    "Retained": true,
    "SingularValue": 88.0386400265,
    "VarianceExplained": 0.01066405
  },
  "a_comp_cor_101": {
    "CumulativeVarianceExplained": 0.4732393263,
    "Mask": "combined",
    "Method": "aCompCor",
    "Retained": true,
    "SingularValue": 87.9873345049,
    "VarianceExplained": 0.0106516244
  },
  "a_comp_cor_102": {
    "CumulativeVarianceExplained": 0.4838752169,
    "Mask": "combined",
    "Method": "aCompCor",
    "Retained": true,
    "SingularValue": 87.9223260431,
    "VarianceExplained": 0.0106358905
  },
  "a_comp_cor_103": {
    "CumulativeVarianceExplained": 0.4944197437,
    "Mask": "combined",
    "Method": "aCompCor",
    "Retained": true,
    "SingularValue": 87.5438791929,
    "VarianceExplained": 0.0105445268
  },
  "a_comp_cor_104": {
    "CumulativeVarianceExplained": 0.5048759091,
    "Mask": "combined",
    "Method": "aCompCor",
    "Retained": true,
    "SingularValue": 87.1763062121,
    "VarianceExplained": 0.0104561655
  },
  "a_comp_cor_11": {
    "CumulativeVarianceExplained": 0.3070049504,
    "Mask": "CSF",
    "Method": "aCompCor",
    "Retained": true,
    "SingularValue": 29.9639504512,
    "VarianceExplained": 0.0156134934
  },
  "a_comp_cor_12": {
    "CumulativeVarianceExplained": 0.3223704255,
    "Mask": "CSF",
    "Method": "aCompCor",
    "Retained": true,
    "SingularValue": 29.7250110322,
    "VarianceExplained": 0.0153654751
  },
  "a_comp_cor_13": {
    "CumulativeVarianceExplained": 0.3374353656,
    "Mask": "CSF",
    "Method": "aCompCor",
    "Retained": true,
    "SingularValue": 29.4328780992,
    "VarianceExplained": 0.0150649401
  },
  "a_comp_cor_14": {
    "CumulativeVarianceExplained": 0.3522599944,
    "Mask": "CSF",
    "Method": "aCompCor",
    "Retained": true,
    "SingularValue": 29.1971823587,
    "VarianceExplained": 0.0148246289
  },
  "a_comp_cor_15": {
    "CumulativeVarianceExplained": 0.3666134326,
    "Mask": "CSF",
    "Method": "aCompCor",
    "Retained": true,
    "SingularValue": 28.7294292946,
    "VarianceExplained": 0.0143534382
  },
  "a_comp_cor_16": {
    "CumulativeVarianceExplained": 0.3808253201,
    "Mask": "CSF",
    "Method": "aCompCor",
    "Retained": true,
    "SingularValue": 28.5874165189,
    "VarianceExplained": 0.0142118876
  },
  "a_comp_cor_17": {
    "CumulativeVarianceExplained": 0.3946878331,
    "Mask": "CSF",
    "Method": "aCompCor",
    "Retained": true,
    "SingularValue": 28.2338439576,
    "VarianceExplained": 0.0138625129
  },
  "a_comp_cor_18": {
    "CumulativeVarianceExplained": 0.4084877156,
    "Mask": "CSF",
    "Method": "aCompCor",
    "Retained": true,
    "SingularValue": 28.1699919519,
    "VarianceExplained": 0.0137998826
  },
  "a_comp_cor_19": {
    "CumulativeVarianceExplained": 0.4219870368,
    "Mask": "CSF",
    "Method": "aCompCor",
    "Retained": true,
    "SingularValue": 27.8615319571,
    "VarianceExplained": 0.0134993211
  },
  "a_comp_cor_20": {
    "CumulativeVarianceExplained": 0.4353847408,
    "Mask": "CSF",
    "Method": "aCompCor",
    "Retained": true,
    "SingularValue": 27.756469042,
    "VarianceExplained": 0.013397704
  },
  "a_comp_cor_21": {
    "CumulativeVarianceExplained": 0.4484035117,
    "Mask": "CSF",
    "Method": "aCompCor",
    "Retained": true,
    "SingularValue": 27.3611293096,
    "VarianceExplained": 0.0130187708
  },
  "a_comp_cor_22": {
    "CumulativeVarianceExplained": 0.4612749998,
    "Mask": "CSF",
    "Method": "aCompCor",
    "Retained": true,
    "SingularValue": 27.2059194387,
    "VarianceExplained": 0.0128714881
  },
  "a_comp_cor_23": {
    "CumulativeVarianceExplained": 0.4739025425,
    "Mask": "CSF",
    "Method": "aCompCor",
    "Retained": true,
    "SingularValue": 26.9468776857,
    "VarianceExplained": 0.0126275427
  },
  "a_comp_cor_24": {
    "CumulativeVarianceExplained": 0.4864143866,
    "Mask": "CSF",
    "Method": "aCompCor",
    "Retained": true,
    "SingularValue": 26.8231445294,
    "VarianceExplained": 0.0125118441
  },
  "a_comp_cor_25": {
    "CumulativeVarianceExplained": 0.4987427835,
    "Mask": "CSF",
    "Method": "aCompCor",
    "Retained": true,
    "SingularValue": 26.6257795789,
    "VarianceExplained": 0.0123283969
  },
  "a_comp_cor_26": {
    "CumulativeVarianceExplained": 0.5108646738,
    "Mask": "CSF",
    "Method": "aCompCor",
    "Retained": true,
    "SingularValue": 26.4018404576,
    "VarianceExplained": 0.0121218903
  },
  "a_comp_cor_27": {
    "CumulativeVarianceExplained": 0.0420137136,
    "Mask": "WM",
    "Method": "aCompCor",
    "Retained": true,
    "SingularValue": 172.1885874771,
    "VarianceExplained": 0.0420137136
  },
  "a_comp_cor_28": {
    "CumulativeVarianceExplained": 0.0632428006,
    "Mask": "WM",
    "Method": "aCompCor",
    "Retained": true,
    "SingularValue": 122.3980462562,
    "VarianceExplained": 0.0212290869
  },
  "a_comp_cor_29": {
    "CumulativeVarianceExplained": 0.0788636475,
    "Mask": "WM",
    "Method": "aCompCor",
    "Retained": true,
    "SingularValue": 104.9931863888,
    "VarianceExplained": 0.0156208469
  },
  "a_comp_cor_30": {
    "CumulativeVarianceExplained": 0.0941936304,
    "Mask": "WM",
    "Method": "aCompCor",
    "Retained": true,
    "SingularValue": 104.0110937875,
    "VarianceExplained": 0.0153299829
  },
  "a_comp_cor_31": {
    "CumulativeVarianceExplained": 0.1083513117,
    "Mask": "WM",
    "Method": "aCompCor",
    "Retained": true,
    "SingularValue": 99.9550850923,
    "VarianceExplained": 0.0141576813
  },
  "a_comp_cor_32": {
    "CumulativeVarianceExplained": 0.1220421856,
    "Mask": "WM",
    "Method": "aCompCor",
    "Retained": true,
    "SingularValue": 98.2934125571,
    "VarianceExplained": 0.0136908739
  },
  "a_comp_cor_33": {
    "CumulativeVarianceExplained": 0.1354675539,
    "Mask": "WM",
    "Method": "aCompCor",
    "Retained": true,
    "SingularValue": 97.3356497049,
    "VarianceExplained": 0.0134253683
  },
  "a_comp_cor_34": {
    "CumulativeVarianceExplained": 0.1485514903,
    "Mask": "WM",
    "Method": "aCompCor",
    "Retained": true,
    "SingularValue": 96.0899663153,
    "VarianceExplained": 0.0130839365
  },
  "a_comp_cor_35": {
    "CumulativeVarianceExplained": 0.161445541,
    "Mask": "WM",
    "Method": "aCompCor",
    "Retained": true,
    "SingularValue": 95.3901460403,
    "VarianceExplained": 0.0128940506
  },
  "a_comp_cor_36": {
    "CumulativeVarianceExplained": 0.1742260325,
    "Mask": "WM",
    "Method": "aCompCor",
    "Retained": true,
    "SingularValue": 94.9691619882,
    "VarianceExplained": 0.0127804915
  },
  "a_comp_cor_37": {
    "CumulativeVarianceExplained": 0.186929353,
    "Mask": "WM",
    "Method": "aCompCor",
    "Retained": true,
    "SingularValue": 94.6820071947,
    "VarianceExplained": 0.0127033205
  },
  "a_comp_cor_38": {
    "CumulativeVarianceExplained": 0.1994771882,
    "Mask": "WM",
    "Method": "aCompCor",
    "Retained": true,
    "SingularValue": 94.1007815244,
    "VarianceExplained": 0.0125478352
  },
  "a_comp_cor_39": {
    "CumulativeVarianceExplained": 0.2118048352,
    "Mask": "WM",
    "Method": "aCompCor",
    "Retained": true,
    "SingularValue": 93.2714918721,
    "VarianceExplained": 0.012327647
  },
  "a_comp_cor_40": {
    "CumulativeVarianceExplained": 0.2240236493,
    "Mask": "WM",
    "Method": "aCompCor",
    "Retained": true,
    "SingularValue": 92.8588618198,
    "VarianceExplained": 0.0122188141
  },
  "a_comp_cor_41": {
    "CumulativeVarianceExplained": 0.2361162042,
    "Mask": "WM",
    "Method": "aCompCor",
    "Retained": true,
    "SingularValue": 92.3778524023,
    "VarianceExplained": 0.0120925549
  },
  "a_comp_cor_42": {
    "CumulativeVarianceExplained": 0.2481303473,
    "Mask": "WM",
    "Method": "aCompCor",
    "Retained": true,
    "SingularValue": 92.0778622899,
    "VarianceExplained": 0.0120141431
  },
  "a_comp_cor_43": {
    "CumulativeVarianceExplained": 0.260050101,
    "Mask": "WM",
    "Method": "aCompCor",
    "Retained": true,
    "SingularValue": 91.715443453,
    "VarianceExplained": 0.0119197538
  },
  "a_comp_cor_44": {
    "CumulativeVarianceExplained": 0.2717927909,
    "Mask": "WM",
    "Method": "aCompCor",
    "Retained": true,
    "SingularValue": 91.0316937674,
    "VarianceExplained": 0.0117426899
  },
  "a_comp_cor_45": {
    "CumulativeVarianceExplained": 0.2834090488,
    "Mask": "WM",
    "Method": "aCompCor",
    "Retained": true,
    "SingularValue": 90.5403045421,
    "VarianceExplained": 0.0116162579
  },
  "a_comp_cor_46": {
    "CumulativeVarianceExplained": 0.2949516147,
    "Mask": "WM",
    "Method": "aCompCor",
    "Retained": true,
    "SingularValue": 90.2526597995,
    "VarianceExplained": 0.0115425659
  },
  "a_comp_cor_47": {
    "CumulativeVarianceExplained": 0.3064860119,
    "Mask": "WM",
    "Method": "aCompCor",
    "Retained": true,
    "SingularValue": 90.2207179892,
    "VarianceExplained": 0.0115343972
  },
  "a_comp_cor_48": {
    "CumulativeVarianceExplained": 0.3179589903,
    "Mask": "WM",
    "Method": "aCompCor",
    "Retained": true,
    "SingularValue": 89.9801918127,
    "VarianceExplained": 0.0114729783
  },
  "a_comp_cor_49": {
    "CumulativeVarianceExplained": 0.3293304911,
    "Mask": "WM",
    "Method": "aCompCor",
    "Retained": true,
    "SingularValue": 89.5813743344,
    "VarianceExplained": 0.0113715008
  },
  "a_comp_cor_50": {
    "CumulativeVarianceExplained": 0.3406369501,
    "Mask": "WM",
    "Method": "aCompCor",
    "Retained": true,
    "SingularValue": 89.3248171007,
    "VarianceExplained": 0.0113064591
  },
  "a_comp_cor_51": {
    "CumulativeVarianceExplained": 0.3518902758,
    "Mask": "WM",
    "Method": "aCompCor",
    "Retained": true,
    "SingularValue": 89.114684119,
    "VarianceExplained": 0.0112533257
  },
  "a_comp_cor_52": {
    "CumulativeVarianceExplained": 0.3631136723,
    "Mask": "WM",
    "Method": "aCompCor",
    "Retained": true,
    "SingularValue": 88.9961008533,
    "VarianceExplained": 0.0112233964
  },
  "a_comp_cor_53": {
    "CumulativeVarianceExplained": 0.3742926204,
    "Mask": "WM",
    "Method": "aCompCor",
    "Retained": true,
    "SingularValue": 88.8196994182,
    "VarianceExplained": 0.0111789482
  },
  "a_comp_cor_54": {
    "CumulativeVarianceExplained": 0.3854389241,
    "Mask": "WM",
    "Method": "aCompCor",
    "Retained": true,
    "SingularValue": 88.6899200038,
    "VarianceExplained": 0.0111463037
  },
  "a_comp_cor_55": {
    "CumulativeVarianceExplained": 0.3964512899,
    "Mask": "WM",
    "Method": "aCompCor",
    "Retained": true,
    "SingularValue": 88.1554452043,
    "VarianceExplained": 0.0110123658
  },
  "a_comp_cor_56": {
    "CumulativeVarianceExplained": 0.4073723602,
    "Mask": "WM",
    "Method": "aCompCor",
    "Retained": true,
    "SingularValue": 87.7892682245,
    "VarianceExplained": 0.0109210703
  },
  "a_comp_cor_57": {
    "CumulativeVarianceExplained": 0.4182784024,
    "Mask": "WM",
    "Method": "aCompCor",
    "Retained": true,
    "SingularValue": 87.7288455914,
    "VarianceExplained": 0.0109060422
  },
  "a_comp_cor_58": {
    "CumulativeVarianceExplained": 0.4291184943,
    "Mask": "WM",
    "Method": "aCompCor",
    "Retained": true,
    "SingularValue": 87.4631893286,
    "VarianceExplained": 0.0108400919
  },
  "a_comp_cor_59": {
    "CumulativeVarianceExplained": 0.439919683,
    "Mask": "WM",
    "Method": "aCompCor",
    "Retained": true,
    "SingularValue": 87.3061031686,
    "VarianceExplained": 0.0108011887
  },
  "a_comp_cor_60": {
    "CumulativeVarianceExplained": 0.4506531556,
    "Mask": "WM",
    "Method": "aCompCor",
    "Retained": true,
    "SingularValue": 87.0319982984,
    "VarianceExplained": 0.0107334727
  },
  "a_comp_cor_61": {
    "CumulativeVarianceExplained": 0.4613735095,
    "Mask": "WM",
    "Method": "aCompCor",
    "Retained": true,
    "SingularValue": 86.9787952476,
    "VarianceExplained": 0.0107203538
  },
  "a_comp_cor_62": {
    "CumulativeVarianceExplained": 0.4720451604,
    "Mask": "WM",
    "Method": "aCompCor",
    "Retained": true,
    "SingularValue": 86.7809966779,
    "VarianceExplained": 0.0106716509
  },
  "a_comp_cor_63": {
    "CumulativeVarianceExplained": 0.4826612596,
    "Mask": "WM",
    "Method": "aCompCor",
    "Retained": true,
    "SingularValue": 86.5548309108,
    "VarianceExplained": 0.0106160992
  },
  "a_comp_cor_64": {
    "CumulativeVarianceExplained": 0.4932319924,
    "Mask": "WM",
    "Method": "aCompCor",
    "Retained": true,
    "SingularValue": 86.3696925681,
    "VarianceExplained": 0.0105707327
  },
  "a_comp_cor_65": {
    "CumulativeVarianceExplained": 0.5037472834,
    "Mask": "WM",
    "Method": "aCompCor",
    "Retained": true,
    "SingularValue": 86.1428975662,
    "VarianceExplained": 0.010515291
  },
  "a_comp_cor_66": {
    "CumulativeVarianceExplained": 0.0413757202,
    "Mask": "combined",
    "Method": "aCompCor",
    "Retained": true,
    "SingularValue": 173.4143461588,
    "VarianceExplained": 0.0413757202
  },
  "a_comp_cor_67": {
    "CumulativeVarianceExplained": 0.0632083595,
    "Mask": "combined",
    "Method": "aCompCor",
    "Retained": true,
    "SingularValue": 125.9694867753,
    "VarianceExplained": 0.0218326393
  },
  "a_comp_cor_68": {
    "CumulativeVarianceExplained": 0.0798105325,
    "Mask": "combined",
    "Method": "aCompCor",
    "Retained": true,
    "SingularValue": 109.8486455711,
    "VarianceExplained": 0.0166021729
  },
  "a_comp_cor_69": {
    "CumulativeVarianceExplained": 0.0951352009,
    "Mask": "combined",
    "Method": "aCompCor",
    "Retained": true,
    "SingularValue": 105.5377383378,
    "VarianceExplained": 0.0153246684
  },
  "a_comp_cor_70": {
    "CumulativeVarianceExplained": 0.1096953279,
    "Mask": "combined",
    "Method": "aCompCor",
    "Retained": true,
    "SingularValue": 102.8714402741,
    "VarianceExplained": 0.0145601269
  },
  "a_comp_cor_71": {
    "CumulativeVarianceExplained": 0.1234949783,
    "Mask": "combined",
    "Method": "aCompCor",
    "Retained": true,
    "SingularValue": 100.1489228596,
    "VarianceExplained": 0.0137996505
  },
  "a_comp_cor_72": {
    "CumulativeVarianceExplained": 0.1371624889,
    "Mask": "combined",
    "Method": "aCompCor",
    "Retained": true,
    "SingularValue": 99.6682767223,
    "VarianceExplained": 0.0136675106
  },
  "a_comp_cor_73": {
    "CumulativeVarianceExplained": 0.1503706407,
    "Mask": "combined",
    "Method": "aCompCor",
    "Retained": true,
    "SingularValue": 97.9790589882,
    "VarianceExplained": 0.0132081517
  },
  "a_comp_cor_74": {
    "CumulativeVarianceExplained": 0.1632881358,
    "Mask": "combined",
    "Method": "aCompCor",
    "Retained": true,
    "SingularValue": 96.8950056676,
    "VarianceExplained": 0.0129174951
  },
  "a_comp_cor_75": {
    "CumulativeVarianceExplained": 0.1761333041,
    "Mask": "combined",
    "Method": "aCompCor",
    "Retained": true,
    "SingularValue": 96.6233607781,
    "VarianceExplained": 0.0128451683
  },
  "a_comp_cor_76": {
    "CumulativeVarianceExplained": 0.1888212406,
    "Mask": "combined",
    "Method": "aCompCor",
    "Retained": true,
    "SingularValue": 96.0301789669,
    "VarianceExplained": 0.0126879365
  },
  "a_comp_cor_77": {
    "CumulativeVarianceExplained": 0.2013817602,
    "Mask": "combined",
    "Method": "aCompCor",
    "Retained": true,
    "SingularValue": 95.5467770026,
    "VarianceExplained": 0.0125605196
  },
  "a_comp_cor_78": {
    "CumulativeVarianceExplained": 0.2137190764,
    "Mask": "combined",
    "Method": "aCompCor",
    "Retained": true,
    "SingularValue": 94.6940276208,
    "VarianceExplained": 0.0123373163
  },
  "a_comp_cor_79": {
    "CumulativeVarianceExplained": 0.2259099779,
    "Mask": "combined",
    "Method": "aCompCor",
    "Retained": true,
    "SingularValue": 94.1304532874,
    "VarianceExplained": 0.0121909015
  },
  "a_comp_cor_80": {
    "CumulativeVarianceExplained": 0.2379788304,
    "Mask": "combined",
    "Method": "aCompCor",
    "Retained": true,
    "SingularValue": 93.6580752764,
    "VarianceExplained": 0.0120688525
  },
  "a_comp_cor_81": {
    "CumulativeVarianceExplained": 0.2499825361,
    "Mask": "combined",
    "Method": "aCompCor",
    "Retained": true,
    "SingularValue": 93.4049537199,
    "VarianceExplained": 0.0120037057
  },
  "a_comp_cor_82": {
    "CumulativeVarianceExplained": 0.261886081,
    "Mask": "combined",
    "Method": "aCompCor",
    "Retained": true,
    "SingularValue": 93.0144445837,
    "VarianceExplained": 0.0119035449
  },
  "a_comp_cor_83": {
    "CumulativeVarianceExplained": 0.2735754667,
    "Mask": "combined",
    "Method": "aCompCor",
    "Retained": true,
    "SingularValue": 92.1739256073,
    "VarianceExplained": 0.0116893857
  },
  "a_comp_cor_84": {
    "CumulativeVarianceExplained": 0.2851975756,
    "Mask": "combined",
    "Method": "aCompCor",
    "Retained": true,
    "SingularValue": 91.9082951606,
    "VarianceExplained": 0.0116221089
  },
  "a_comp_cor_85": {
    "CumulativeVarianceExplained": 0.296768569,
    "Mask": "combined",
    "Method": "aCompCor",
    "Retained": true,
    "SingularValue": 91.7059599596,
    "VarianceExplained": 0.0115709933
  },
  "a_comp_cor_86": {
    "CumulativeVarianceExplained": 0.3082905564,
    "Mask": "combined",
    "Method": "aCompCor",
    "Retained": true,
    "SingularValue": 91.5115555907,
    "VarianceExplained": 0.0115219874
  },
  "a_comp_cor_87": {
    "CumulativeVarianceExplained": 0.3196976318,
    "Mask": "combined",
    "Method": "aCompCor",
    "Retained": true,
    "SingularValue": 91.054077053,
    "VarianceExplained": 0.0114070754
  },
  "a_comp_cor_88": {
    "CumulativeVarianceExplained": 0.3310429512,
    "Mask": "combined",
    "Method": "aCompCor",
    "Retained": true,
    "SingularValue": 90.8072663779,
    "VarianceExplained": 0.0113453193
  },
  "a_comp_cor_89": {
    "CumulativeVarianceExplained": 0.3423572988,
    "Mask": "combined",
    "Method": "aCompCor",
    "Retained": true,
    "SingularValue": 90.6832339189,
    "VarianceExplained": 0.0113143477
  },
  "a_comp_cor_90": {
    "CumulativeVarianceExplained": 0.3535563741,
    "Mask": "combined",
    "Method": "aCompCor",
    "Retained": true,
    "SingularValue": 90.2201035435,
    "VarianceExplained": 0.0111990753
  },
  "a_comp_cor_91": {
    "CumulativeVarianceExplained": 0.3647362713,
    "Mask": "combined",
    "Method": "aCompCor",
    "Retained": true,
    "SingularValue": 90.1428208494,
    "VarianceExplained": 0.0111798972
  },
  "a_comp_cor_92": {
    "CumulativeVarianceExplained": 0.3758542344,
    "Mask": "combined",
    "Method": "aCompCor",
    "Retained": true,
    "SingularValue": 89.8927886175,
    "VarianceExplained": 0.0111179631
  },
  "a_comp_cor_93": {
    "CumulativeVarianceExplained": 0.3869409132,
    "Mask": "combined",
    "Method": "aCompCor",
    "Retained": true,
    "SingularValue": 89.7662272909,
    "VarianceExplained": 0.0110866788
  },
  "a_comp_cor_94": {
    "CumulativeVarianceExplained": 0.3979122438,
    "Mask": "combined",
    "Method": "aCompCor",
    "Retained": true,
    "SingularValue": 89.2980326849,
    "VarianceExplained": 0.0109713306
  },
  "a_comp_cor_95": {
    "CumulativeVarianceExplained": 0.4087797714,
    "Mask": "combined",
    "Method": "aCompCor",
    "Retained": true,
    "SingularValue": 88.8745912101,
    "VarianceExplained": 0.0108675276
  },
  "a_comp_cor_96": {
    "CumulativeVarianceExplained": 0.4196284087,
    "Mask": "combined",
    "Method": "aCompCor",
    "Retained": true,
    "SingularValue": 88.7973151214,
    "VarianceExplained": 0.0108486373
  },
  "a_comp_cor_97": {
    "CumulativeVarianceExplained": 0.4304518246,
    "Mask": "combined",
    "Method": "aCompCor",
    "Retained": true,
    "SingularValue": 88.6940347319,
    "VarianceExplained": 0.0108234158
  },
  "a_comp_cor_98": {
    "CumulativeVarianceExplained": 0.4412131482,
    "Mask": "combined",
    "Method": "aCompCor",
    "Retained": true,
    "SingularValue": 88.4392570037,
    "VarianceExplained": 0.0107613236
  },
  "a_comp_cor_99": {
    "CumulativeVarianceExplained": 0.451923652,
    "Mask": "combined",
    "Method": "aCompCor",
    "Retained": true,
    "SingularValue": 88.2301848844,
    "VarianceExplained": 0.0107105038
  },
  "csf": {
    "Method": "Mean"
  },
  "csf_wm": {
    "Method": "Mean"
  },
  "dropped_0": {
    "CumulativeVarianceExplained": 0.5228197313,
    "Mask": "CSF",
    "Method": "aCompCor",
    "Retained": false,
    "SingularValue": 26.219527575,
    "VarianceExplained": 0.0119550575
  },
  "dropped_1": {
    "CumulativeVarianceExplained": 0.5345384454,
    "Mask": "CSF",
    "Method": "aCompCor",
    "Retained": false,
    "SingularValue": 25.9590626105,
    "VarianceExplained": 0.011718714
  },
  "dropped_10": {
    "CumulativeVarianceExplained": 0.6325781226,
    "Mask": "CSF",
    "Method": "aCompCor",
    "Retained": false,
    "SingularValue": 24.1523038945,
    "VarianceExplained": 0.0101442297
  },
  "dropped_100": {
    "CumulativeVarianceExplained": 0.8162161706,
    "Mask": "WM",
    "Method": "aCompCor",
    "Retained": false,
    "SingularValue": 80.1869626806,
    "VarianceExplained": 0.0091114998
  },
  "dropped_101": {
    "CumulativeVarianceExplained": 0.8252507159,
    "Mask": "WM",
    "Method": "aCompCor",
    "Retained": false,
    "SingularValue": 79.847620649,
    "VarianceExplained": 0.0090345454
  },
  "dropped_102": {
    "CumulativeVarianceExplained": 0.8342793202,
    "Mask": "WM",
    "Method": "aCompCor",
    "Retained": false,
    "SingularValue": 79.8213624556,
    "VarianceExplained": 0.0090286042
  },
  "dropped_103": {
    "CumulativeVarianceExplained": 0.8432470538,
    "Mask": "WM",
    "Method": "aCompCor",
    "Retained": false,
    "SingularValue": 79.5518304666,
    "VarianceExplained": 0.0089677336
  },
  "dropped_104": {
    "CumulativeVarianceExplained": 0.852159872,
    "Mask": "WM",
    "Method": "aCompCor",
    "Retained": false,
    "SingularValue": 79.3078822057,
    "VarianceExplained": 0.0089128182
  },
  "dropped_105": {
    "CumulativeVarianceExplained": 0.860999471,
    "Mask": "WM",
    "Method": "aCompCor",
    "Retained": false,
    "SingularValue": 78.9814514496,
    "VarianceExplained": 0.008839599
  },
  "dropped_106": {
    "CumulativeVarianceExplained": 0.8698365889,
    "Mask": "WM",
    "Method": "aCompCor",
    "Retained": false,
    "SingularValue": 78.9703663141,
    "VarianceExplained": 0.0088371179
  },
  "dropped_107": {
    "CumulativeVarianceExplained": 0.8786334946,
    "Mask": "WM",
    "Method": "aCompCor",
    "Retained": false,
    "SingularValue": 78.7904890259,
    "VarianceExplained": 0.0087969057
  },
  "dropped_108": {
    "CumulativeVarianceExplained": 0.887342523,
    "Mask": "WM",
    "Method": "aCompCor",
    "Retained": false,
    "SingularValue": 78.395959462,
    "VarianceExplained": 0.0087090283
  },
  "dropped_109": {
    "CumulativeVarianceExplained": 0.8960371517,
    "Mask": "WM",
    "Method": "aCompCor",
    "Retained": false,
    "SingularValue": 78.3311221147,
    "VarianceExplained": 0.0086946287
  },
  "dropped_11": {
    "CumulativeVarianceExplained": 0.642626084,
    "Mask": "CSF",
    "Method": "aCompCor",
    "Retained": false,
    "SingularValue": 24.0374286778,
    "VarianceExplained": 0.0100479615
  },
  "dropped_110": {
    "CumulativeVarianceExplained": 0.9047087493,
    "Mask": "WM",
    "Method": "aCompCor",
    "Retained": false,
    "SingularValue": 78.227308475,
    "VarianceExplained": 0.0086715977
  },
  "dropped_111": {
    "CumulativeVarianceExplained": 0.9132958099,
    "Mask": "WM",
    "Method": "aCompCor",
    "Retained": false,
    "SingularValue": 77.8450660837,
    "VarianceExplained": 0.0085870606
  },
  "dropped_112": {
    "CumulativeVarianceExplained": 0.9218593683,
    "Mask": "WM",
    "Method": "aCompCor",
    "Retained": false,
    "SingularValue": 77.7384645695,
    "VarianceExplained": 0.0085635584
  },
  "dropped_113": {
    "CumulativeVarianceExplained": 0.9304105376,
    "Mask": "WM",
    "Method": "aCompCor",
    "Retained": false,
    "SingularValue": 77.6822115704,
    "VarianceExplained": 0.0085511693
  },
  "dropped_114": {
    "CumulativeVarianceExplained": 0.9387945083,
    "Mask": "WM",
    "Method": "aCompCor",
    "Retained": false,
    "SingularValue": 76.9190130798,
    "VarianceExplained": 0.0083839707
  },
  "dropped_115": {
    "CumulativeVarianceExplained": 0.9471257823,
    "Mask": "WM",
    "Method": "aCompCor",
    "Retained": false,
    "SingularValue": 76.676898216,
    "VarianceExplained": 0.008331274
  },
  "dropped_116": {
    "CumulativeVarianceExplained": 0.9553584571,
    "Mask": "WM",
    "Method": "aCompCor",
    "Retained": false,
    "SingularValue": 76.2218191388,
    "VarianceExplained": 0.0082326749
  },
  "dropped_117": {
    "CumulativeVarianceExplained": 0.9635701246,
    "Mask": "WM",
    "Method": "aCompCor",
    "Retained": false,
    "SingularValue": 76.1245089794,
    "VarianceExplained": 0.0082116674
  },
  "dropped_118": {
    "CumulativeVarianceExplained": 0.9716668552,
    "Mask": "WM",
    "Method": "aCompCor",
    "Retained": false,
    "SingularValue": 75.5898829107,
    "VarianceExplained": 0.0080967306
  },
  "dropped_119": {
    "CumulativeVarianceExplained": 0.9796940522,
    "Mask": "WM",
    "Method": "aCompCor",
    "Retained": false,
    "SingularValue": 75.2646053392,
    "VarianceExplained": 0.008027197
  },
  "dropped_12": {
    "CumulativeVarianceExplained": 0.652617676,
    "Mask": "CSF",
    "Method": "aCompCor",
    "Retained": false,
    "SingularValue": 23.9699083399,
    "VarianceExplained": 0.009991592
  },
  "dropped_120": {
    "CumulativeVarianceExplained": 0.9876026333,
    "Mask": "WM",
    "Method": "aCompCor",
    "Retained": false,
    "SingularValue": 74.7064528862,
    "VarianceExplained": 0.0079085812
  },
  "dropped_121": {
    "CumulativeVarianceExplained": 0.994636527,
    "Mask": "WM",
    "Method": "aCompCor",
    "Retained": false,
    "SingularValue": 70.4541740033,
    "VarianceExplained": 0.0070338937
  },
  "dropped_122": {
    "CumulativeVarianceExplained": 1.0,
    "Mask": "WM",
    "Method": "aCompCor",
    "Retained": false,
    "SingularValue": 61.5222026902,
    "VarianceExplained": 0.005363473
  },
  "dropped_123": {
    "CumulativeVarianceExplained": 1.0,
    "Mask": "WM",
    "Method": "aCompCor",
    "Retained": false,
    "SingularValue": 0.0,
    "VarianceExplained": 0.0
  },
  "dropped_124": {
    "CumulativeVarianceExplained": 1.0,
    "Mask": "WM",
    "Method": "aCompCor",
    "Retained": false,
    "SingularValue": 0.0,
    "VarianceExplained": 0.0
  },
  "dropped_125": {
    "CumulativeVarianceExplained": 1.0,
    "Mask": "WM",
    "Method": "aCompCor",
    "Retained": false,
    "SingularValue": 0.0,
    "VarianceExplained": 0.0
  },
  "dropped_126": {
    "CumulativeVarianceExplained": 0.515317571,
    "Mask": "combined",
    "Method": "aCompCor",
    "Retained": false,
    "SingularValue": 87.1158248335,
    "VarianceExplained": 0.0104416619
  },
  "dropped_127": {
    "CumulativeVarianceExplained": 0.525676472,
    "Mask": "combined",
    "Method": "aCompCor",
    "Retained": false,
    "SingularValue": 86.769896707,
    "VarianceExplained": 0.010358901
  },
  "dropped_128": {
    "CumulativeVarianceExplained": 0.5359808403,
    "Mask": "combined",
    "Method": "aCompCor",
    "Retained": false,
    "SingularValue": 86.5412023706,
    "VarianceExplained": 0.0103043682
  },
  "dropped_129": {
    "CumulativeVarianceExplained": 0.5462436934,
    "Mask": "combined",
    "Method": "aCompCor",
    "Retained": false,
    "SingularValue": 86.3666943441,
    "VarianceExplained": 0.0102628532
  },
  "dropped_13": {
    "CumulativeVarianceExplained": 0.6624566871,
    "Mask": "CSF",
    "Method": "aCompCor",
    "Retained": false,
    "SingularValue": 23.7861827873,
    "VarianceExplained": 0.0098390111
  },
  "dropped_130": {
    "CumulativeVarianceExplained": 0.5564836846,
    "Mask": "combined",
    "Method": "aCompCor",
    "Retained": false,
    "SingularValue": 86.2704435176,
    "VarianceExplained": 0.0102399912
  },
  "dropped_131": {
    "CumulativeVarianceExplained": 0.5666908273,
    "Mask": "combined",
    "Method": "aCompCor",
    "Retained": false,
    "SingularValue": 86.131960362,
    "VarianceExplained": 0.0102071427
  },
  "dropped_132": {
    "CumulativeVarianceExplained": 0.5768282098,
    "Mask": "combined",
    "Method": "aCompCor",
    "Retained": false,
    "SingularValue": 85.8371237345,
    "VarianceExplained": 0.0101373825
  },
  "dropped_133": {
    "CumulativeVarianceExplained": 0.5869559905,
    "Mask": "combined",
    "Method": "aCompCor",
    "Retained": false,
    "SingularValue": 85.7964632,
    "VarianceExplained": 0.0101277808
  },
  "dropped_134": {
    "CumulativeVarianceExplained": 0.5970337318,
    "Mask": "combined",
    "Method": "aCompCor",
    "Retained": false,
    "SingularValue": 85.5842484067,
    "VarianceExplained": 0.0100777412
  },
  "dropped_135": {
    "CumulativeVarianceExplained": 0.6070625896,
    "Mask": "combined",
    "Method": "aCompCor",
    "Retained": false,
    "SingularValue": 85.3764273831,
    "VarianceExplained": 0.0100288579
  },
  "dropped_136": {
    "CumulativeVarianceExplained": 0.6170272963,
    "Mask": "combined",
    "Method": "aCompCor",
    "Retained": false,
    "SingularValue": 85.1029273613,
    "VarianceExplained": 0.0099647067
  },
  "dropped_137": {
    "CumulativeVarianceExplained": 0.6269258762,
    "Mask": "combined",
    "Method": "aCompCor",
    "Retained": false,
    "SingularValue": 84.8200817189,
    "VarianceExplained": 0.0098985799
  },
  "dropped_138": {
    "CumulativeVarianceExplained": 0.6367832769,
    "Mask": "combined",
    "Method": "aCompCor",
    "Retained": false,
    "SingularValue": 84.6434673763,
    "VarianceExplained": 0.0098574007
  },
  "dropped_139": {
    "CumulativeVarianceExplained": 0.6465774429,
    "Mask": "combined",
    "Method": "aCompCor",
    "Retained": false,
    "SingularValue": 84.3715385155,
    "VarianceExplained": 0.0097941659
  },
  "dropped_14": {
    "CumulativeVarianceExplained": 0.6720759467,
    "Mask": "CSF",
    "Method": "aCompCor",
    "Retained": false,
    "SingularValue": 23.5190540216,
    "VarianceExplained": 0.0096192596
  },
  "dropped_140": {
    "CumulativeVarianceExplained": 0.6563552557,
    "Mask": "combined",
    "Method": "aCompCor",
    "Retained": false,
    "SingularValue": 84.3010721607,
    "VarianceExplained": 0.0097778128
  },
  "dropped_141": {
    "CumulativeVarianceExplained": 0.6661002083,
    "Mask": "combined",
    "Method": "aCompCor",
    "Retained": false,
    "SingularValue": 84.1592981659,
    "VarianceExplained": 0.0097449526
  },
  "dropped_142": {
    "CumulativeVarianceExplained": 0.675810626,
    "Mask": "combined",
    "Method": "aCompCor",
    "Retained": false,
    "SingularValue": 84.0100409082,
    "VarianceExplained": 0.0097104177
  },
  "dropped_143": {
    "CumulativeVarianceExplained": 0.6854809527,
    "Mask": "combined",
    "Method": "aCompCor",
    "Retained": false,
    "SingularValue": 83.8364370318,
    "VarianceExplained": 0.0096703267
  },
  "dropped_144": {
    "CumulativeVarianceExplained": 0.6950990795,
    "Mask": "combined",
    "Method": "aCompCor",
    "Retained": false,
    "SingularValue": 83.609858456,
    "VarianceExplained": 0.0096181268
  },
  "dropped_145": {
    "CumulativeVarianceExplained": 0.7046845669,
    "Mask": "combined",
    "Method": "aCompCor",
    "Retained": false,
    "SingularValue": 83.4678720605,
    "VarianceExplained": 0.0095854875
  },
  "dropped_146": {
    "CumulativeVarianceExplained": 0.7142509582,
    "Mask": "combined",
    "Method": "aCompCor",
    "Retained": false,
    "SingularValue": 83.3846881082,
    "VarianceExplained": 0.0095663912
  },
  "dropped_147": {
    "CumulativeVarianceExplained": 0.7237778853,
    "Mask": "combined",
    "Method": "aCompCor",
    "Retained": false,
    "SingularValue": 83.2125174366,
    "VarianceExplained": 0.0095269271
  },
  "dropped_148": {
    "CumulativeVarianceExplained": 0.7332563292,
    "Mask": "combined",
    "Method": "aCompCor",
    "Retained": false,
    "SingularValue": 83.0005103023,
    "VarianceExplained": 0.0094784439
  },
  "dropped_149": {
    "CumulativeVarianceExplained": 0.7427113532,
    "Mask": "combined",
    "Method": "aCompCor",
    "Retained": false,
    "SingularValue": 82.8979051597,
    "VarianceExplained": 0.0094550239
  },
  "dropped_15": {
    "CumulativeVarianceExplained": 0.6816843119,
    "Mask": "CSF",
    "Method": "aCompCor",
    "Retained": false,
    "SingularValue": 23.5057319668,
    "VarianceExplained": 0.0096083652
  },
  "dropped_150": {
    "CumulativeVarianceExplained": 0.7520891462,
    "Mask": "combined",
    "Method": "aCompCor",
    "Retained": false,
    "SingularValue": 82.5586460535,
    "VarianceExplained": 0.0093777931
  },
  "dropped_151": {
    "CumulativeVarianceExplained": 0.7614301995,
    "Mask": "combined",
    "Method": "aCompCor",
    "Retained": false,
    "SingularValue": 82.3967655074,
    "VarianceExplained": 0.0093410533
  },
  "dropped_152": {
    "CumulativeVarianceExplained": 0.7707488948,
    "Mask": "combined",
    "Method": "aCompCor",
    "Retained": false,
    "SingularValue": 82.2980973775,
    "VarianceExplained": 0.0093186953
  },
  "dropped_153": {
    "CumulativeVarianceExplained": 0.7800366126,
    "Mask": "combined",
    "Method": "aCompCor",
    "Retained": false,
    "SingularValue": 82.1611945994,
    "VarianceExplained": 0.0092877178
  },
  "dropped_154": {
    "CumulativeVarianceExplained": 0.7892724084,
    "Mask": "combined",
    "Method": "aCompCor",
    "Retained": false,
    "SingularValue": 81.9312161383,
    "VarianceExplained": 0.0092357958
  },
  "dropped_155": {
    "CumulativeVarianceExplained": 0.7984489945,
    "Mask": "combined",
    "Method": "aCompCor",
    "Retained": false,
    "SingularValue": 81.6681676894,
    "VarianceExplained": 0.0091765861
  },
  "dropped_156": {
    "CumulativeVarianceExplained": 0.80755266,
    "Mask": "combined",
    "Method": "aCompCor",
    "Retained": false,
    "SingularValue": 81.343037291,
    "VarianceExplained": 0.0091036655
  },
  "dropped_157": {
    "CumulativeVarianceExplained": 0.8166138073,
    "Mask": "combined",
    "Method": "aCompCor",
    "Retained": false,
    "SingularValue": 81.1528610275,
    "VarianceExplained": 0.0090611473
  },
  "dropped_158": {
    "CumulativeVarianceExplained": 0.8256307704,
    "Mask": "combined",
    "Method": "aCompCor",
    "Retained": false,
    "SingularValue": 80.9547593044,
    "VarianceExplained": 0.0090169631
  },
  "dropped_159": {
    "CumulativeVarianceExplained": 0.8345940841,
    "Mask": "combined",
    "Method": "aCompCor",
    "Retained": false,
    "SingularValue": 80.7135664971,
    "VarianceExplained": 0.0089633137
  },
  "dropped_16": {
    "CumulativeVarianceExplained": 0.6911013328,
    "Mask": "CSF",
    "Method": "aCompCor",
    "Retained": false,
    "SingularValue": 23.2705042436,
    "VarianceExplained": 0.0094170209
  },
  "dropped_160": {
    "CumulativeVarianceExplained": 0.8435197233,
    "Mask": "combined",
    "Method": "aCompCor",
    "Retained": false,
    "SingularValue": 80.5437606555,
    "VarianceExplained": 0.0089256392
  },
  "dropped_161": {
    "CumulativeVarianceExplained": 0.8524279779,
    "Mask": "combined",
    "Method": "aCompCor",
    "Retained": false,
    "SingularValue": 80.4652844619,
    "VarianceExplained": 0.0089082546
  },
  "dropped_162": {
    "CumulativeVarianceExplained": 0.8613142446,
    "Mask": "combined",
    "Method": "aCompCor",
    "Retained": false,
    "SingularValue": 80.3659180822,
    "VarianceExplained": 0.0088862667
  },
  "dropped_163": {
    "CumulativeVarianceExplained": 0.8701173609,
    "Mask": "combined",
    "Method": "aCompCor",
    "Retained": false,
    "SingularValue": 79.9890354811,
    "VarianceExplained": 0.0088031163
  },
  "dropped_164": {
    "CumulativeVarianceExplained": 0.8788846305,
    "Mask": "combined",
    "Method": "aCompCor",
    "Retained": false,
    "SingularValue": 79.8260096832,
    "VarianceExplained": 0.0087672696
  },
  "dropped_165": {
    "CumulativeVarianceExplained": 0.8875801651,
    "Mask": "combined",
    "Method": "aCompCor",
    "Retained": false,
    "SingularValue": 79.4987652896,
    "VarianceExplained": 0.0086955346
  },
  "dropped_166": {
    "CumulativeVarianceExplained": 0.8962496604,
    "Mask": "combined",
    "Method": "aCompCor",
    "Retained": false,
    "SingularValue": 79.3796439265,
    "VarianceExplained": 0.0086694953
  },
  "dropped_167": {
    "CumulativeVarianceExplained": 0.9048706814,
    "Mask": "combined",
    "Method": "aCompCor",
    "Retained": false,
    "SingularValue": 79.1574127423,
    "VarianceExplained": 0.008621021
  },
  "dropped_168": {
    "CumulativeVarianceExplained": 0.9134514843,
    "Mask": "combined",
    "Method": "aCompCor",
    "Retained": false,
    "SingularValue": 78.9725574452,
    "VarianceExplained": 0.0085808029
  },
  "dropped_169": {
    "CumulativeVarianceExplained": 0.9219841562,
    "Mask": "combined",
    "Method": "aCompCor",
    "Retained": false,
    "SingularValue": 78.7507619399,
    "VarianceExplained": 0.008532672
  },
  "dropped_17": {
    "CumulativeVarianceExplained": 0.7003317895,
    "Mask": "CSF",
    "Method": "aCompCor",
    "Retained": false,
    "SingularValue": 23.038840712,
    "VarianceExplained": 0.0092304567
  },
  "dropped_170": {
    "CumulativeVarianceExplained": 0.9305089392,
    "Mask": "combined",
    "Method": "aCompCor",
    "Retained": false,
    "SingularValue": 78.714348481,
    "VarianceExplained": 0.008524783
  },
  "dropped_171": {
    "CumulativeVarianceExplained": 0.938895192,
    "Mask": "combined",
    "Method": "aCompCor",
    "Retained": false,
    "SingularValue": 78.0721632728,
    "VarianceExplained": 0.0083862527
  },
  "dropped_172": {
    "CumulativeVarianceExplained": 0.9472441772,
    "Mask": "combined",
    "Method": "aCompCor",
    "Retained": false,
    "SingularValue": 77.898498425,
    "VarianceExplained": 0.0083489852
  },
  "dropped_173": {
    "CumulativeVarianceExplained": 0.9554811813,
    "Mask": "combined",
    "Method": "aCompCor",
    "Retained": false,
    "SingularValue": 77.3743265254,
    "VarianceExplained": 0.0082370041
  },
  "dropped_174": {
    "CumulativeVarianceExplained": 0.9636785114,
    "Mask": "combined",
    "Method": "aCompCor",
    "Retained": false,
    "SingularValue": 77.1877621917,
    "VarianceExplained": 0.00819733
  },
  "dropped_175": {
    "CumulativeVarianceExplained": 0.9717305349,
    "Mask": "combined",
    "Method": "aCompCor",
    "Retained": false,
    "SingularValue": 76.5005851175,
    "VarianceExplained": 0.0080520235
  },
  "dropped_176": {
    "CumulativeVarianceExplained": 0.9797224875,
    "Mask": "combined",
    "Method": "aCompCor",
    "Retained": false,
    "SingularValue": 76.2146903774,
    "VarianceExplained": 0.0079919526
  },
  "dropped_177": {
    "CumulativeVarianceExplained": 0.9876190425,
    "Mask": "combined",
    "Method": "aCompCor",
    "Retained": false,
    "SingularValue": 75.7584485161,
    "VarianceExplained": 0.007896555
  },
  "dropped_178": {
    "CumulativeVarianceExplained": 0.9946577478,
    "Mask": "combined",
    "Method": "aCompCor",
    "Retained": false,
    "SingularValue": 71.5251256686,
    "VarianceExplained": 0.0070387053
  },
  "dropped_179": {
    "CumulativeVarianceExplained": 1.0,
    "Mask": "combined",
    "Method": "aCompCor",
    "Retained": false,
    "SingularValue": 62.3123935435,
    "VarianceExplained": 0.0053422522
  },
  "dropped_18": {
    "CumulativeVarianceExplained": 0.7093823451,
    "Mask": "CSF",
    "Method": "aCompCor",
    "Retained": false,
    "SingularValue": 22.8132231807,
    "VarianceExplained": 0.0090505556
  },
  "dropped_180": {
    "CumulativeVarianceExplained": 1.0,
    "Mask": "combined",
    "Method": "aCompCor",
    "Retained": false,
    "SingularValue": 0.0,
    "VarianceExplained": 0.0
  },
  "dropped_181": {
    "CumulativeVarianceExplained": 1.0,
    "Mask": "combined",
    "Method": "aCompCor",
    "Retained": false,
    "SingularValue": 0.0,
    "VarianceExplained": 0.0
  },
  "dropped_182": {
    "CumulativeVarianceExplained": 1.0,
    "Mask": "combined",
    "Method": "aCompCor",
    "Retained": false,
    "SingularValue": 0.0,
    "VarianceExplained": 0.0
  },
  "dropped_19": {
    "CumulativeVarianceExplained": 0.7182813431,
    "Mask": "CSF",
    "Method": "aCompCor",
    "Retained": false,
    "SingularValue": 22.621405356,
    "VarianceExplained": 0.008898998
  },
  "dropped_2": {
    "CumulativeVarianceExplained": 0.5461182804,
    "Mask": "CSF",
    "Method": "aCompCor",
    "Retained": false,
    "SingularValue": 25.8047832,
    "VarianceExplained": 0.0115798351
  },
  "dropped_20": {
    "CumulativeVarianceExplained": 0.7270181274,
    "Mask": "CSF",
    "Method": "aCompCor",
    "Retained": false,
    "SingularValue": 22.4142821983,
    "VarianceExplained": 0.0087367843
  },
  "dropped_21": {
    "CumulativeVarianceExplained": 0.7355803973,
    "Mask": "CSF",
    "Method": "aCompCor",
    "Retained": false,
    "SingularValue": 22.189293993,
    "VarianceExplained": 0.0085622699
  },
  "dropped_22": {
    "CumulativeVarianceExplained": 0.7440180889,
    "Mask": "CSF",
    "Method": "aCompCor",
    "Retained": false,
    "SingularValue": 22.0272789704,
    "VarianceExplained": 0.0084376916
  },
  "dropped_23": {
    "CumulativeVarianceExplained": 0.75236658,
    "Mask": "CSF",
    "Method": "aCompCor",
    "Retained": false,
    "SingularValue": 21.9105370141,
    "VarianceExplained": 0.0083484911
  },
  "dropped_24": {
    "CumulativeVarianceExplained": 0.7606096366,
    "Mask": "CSF",
    "Method": "aCompCor",
    "Retained": false,
    "SingularValue": 21.77174137,
    "VarianceExplained": 0.0082430565
  },
  "dropped_25": {
    "CumulativeVarianceExplained": 0.7687457097,
    "Mask": "CSF",
    "Method": "aCompCor",
    "Retained": false,
    "SingularValue": 21.6299965451,
    "VarianceExplained": 0.0081360732
  },
  "dropped_26": {
    "CumulativeVarianceExplained": 0.7767591575,
    "Mask": "CSF",
    "Method": "aCompCor",
    "Retained": false,
    "SingularValue": 21.4663761371,
    "VarianceExplained": 0.0080134478
  },
  "dropped_27": {
    "CumulativeVarianceExplained": 0.7845804567,
    "Mask": "CSF",
    "Method": "aCompCor",
    "Retained": false,
    "SingularValue": 21.2074512054,
    "VarianceExplained": 0.0078212992
  },
  "dropped_28": {
    "CumulativeVarianceExplained": 0.7922653987,
    "Mask": "CSF",
    "Method": "aCompCor",
    "Retained": false,
    "SingularValue": 21.0217721854,
    "VarianceExplained": 0.007684942
  },
  "dropped_29": {
    "CumulativeVarianceExplained": 0.7998910787,
    "Mask": "CSF",
    "Method": "aCompCor",
    "Retained": false,
    "SingularValue": 20.9405611248,
    "VarianceExplained": 0.00762568
  },
  "dropped_3": {
    "CumulativeVarianceExplained": 0.5575009709,
    "Mask": "CSF",
    "Method": "aCompCor",
    "Retained": false,
    "SingularValue": 25.584179391,
    "VarianceExplained": 0.0113826905
  },
  "dropped_30": {
    "CumulativeVarianceExplained": 0.8073207352,
    "Mask": "CSF",
    "Method": "aCompCor",
    "Retained": false,
    "SingularValue": 20.6696630251,
    "VarianceExplained": 0.0074296565
  },
  "dropped_31": {
    "CumulativeVarianceExplained": 0.8146873636,
    "Mask": "CSF",
    "Method": "aCompCor",
    "Retained": false,
    "SingularValue": 20.5818026332,
    "VarianceExplained": 0.0073666284
  },
  "dropped_32": {
    "CumulativeVarianceExplained": 0.8218442314,
    "Mask": "CSF",
    "Method": "aCompCor",
    "Retained": false,
    "SingularValue": 20.2866587966,
    "VarianceExplained": 0.0071568678
  },
  "dropped_33": {
    "CumulativeVarianceExplained": 0.8289241854,
    "Mask": "CSF",
    "Method": "aCompCor",
    "Retained": false,
    "SingularValue": 20.1773554257,
    "VarianceExplained": 0.007079954
  },
  "dropped_34": {
    "CumulativeVarianceExplained": 0.8358752147,
    "Mask": "CSF",
    "Method": "aCompCor",
    "Retained": false,
    "SingularValue": 19.9927984764,
    "VarianceExplained": 0.0069510293
  },
  "dropped_35": {
    "CumulativeVarianceExplained": 0.8427047392,
    "Mask": "CSF",
    "Method": "aCompCor",
    "Retained": false,
    "SingularValue": 19.8172898073,
    "VarianceExplained": 0.0068295245
  },
  "dropped_36": {
    "CumulativeVarianceExplained": 0.8494472086,
    "Mask": "CSF",
    "Method": "aCompCor",
    "Retained": false,
    "SingularValue": 19.6905805923,
    "VarianceExplained": 0.0067424695
  },
  "dropped_37": {
    "CumulativeVarianceExplained": 0.8561249572,
    "Mask": "CSF",
    "Method": "aCompCor",
    "Retained": false,
    "SingularValue": 19.5958479458,
    "VarianceExplained": 0.0066777486
  },
  "dropped_38": {
    "CumulativeVarianceExplained": 0.8627316727,
    "Mask": "CSF",
    "Method": "aCompCor",
    "Retained": false,
    "SingularValue": 19.4913459274,
    "VarianceExplained": 0.0066067155
  },
  "dropped_39": {
    "CumulativeVarianceExplained": 0.8692604805,
    "Mask": "CSF",
    "Method": "aCompCor",
    "Retained": false,
    "SingularValue": 19.3760821829,
    "VarianceExplained": 0.0065288077
  },
  "dropped_4": {
    "CumulativeVarianceExplained": 0.5687992015,
    "Mask": "CSF",
    "Method": "aCompCor",
    "Retained": false,
    "SingularValue": 25.4890849161,
    "VarianceExplained": 0.0112982306
  },
  "dropped_40": {
    "CumulativeVarianceExplained": 0.8756731838,
    "Mask": "CSF",
    "Method": "aCompCor",
    "Retained": false,
    "SingularValue": 19.2030230337,
    "VarianceExplained": 0.0064127034
  },
  "dropped_41": {
    "CumulativeVarianceExplained": 0.8819529686,
    "Mask": "CSF",
    "Method": "aCompCor",
    "Retained": false,
    "SingularValue": 19.0029667378,
    "VarianceExplained": 0.0062797848
  },
  "dropped_42": {
    "CumulativeVarianceExplained": 0.888133836,
    "Mask": "CSF",
    "Method": "aCompCor",
    "Retained": false,
    "SingularValue": 18.8527079422,
    "VarianceExplained": 0.0061808674
  },
  "dropped_43": {
    "CumulativeVarianceExplained": 0.8942160032,
    "Mask": "CSF",
    "Method": "aCompCor",
    "Retained": false,
    "SingularValue": 18.7015759921,
    "VarianceExplained": 0.0060821672
  },
  "dropped_44": {
    "CumulativeVarianceExplained": 0.9001489587,
    "Mask": "CSF",
    "Method": "aCompCor",
    "Retained": false,
    "SingularValue": 18.4707518707,
    "VarianceExplained": 0.0059329555
  },
  "dropped_45": {
    "CumulativeVarianceExplained": 0.9060379487,
    "Mask": "CSF",
    "Method": "aCompCor",
    "Retained": false,
    "SingularValue": 18.4021868187,
    "VarianceExplained": 0.00588899
  },
  "dropped_46": {
    "CumulativeVarianceExplained": 0.9118370141,
    "Mask": "CSF",
    "Method": "aCompCor",
    "Retained": false,
    "SingularValue": 18.2611461539,
    "VarianceExplained": 0.0057990654
  },
  "dropped_47": {
    "CumulativeVarianceExplained": 0.9175478724,
    "Mask": "CSF",
    "Method": "aCompCor",
    "Retained": false,
    "SingularValue": 18.1217325947,
    "VarianceExplained": 0.0057108582
  },
  "dropped_48": {
    "CumulativeVarianceExplained": 0.9231051228,
    "Mask": "CSF",
    "Method": "aCompCor",
    "Retained": false,
    "SingularValue": 17.8763567127,
    "VarianceExplained": 0.0055572504
  },
  "dropped_49": {
    "CumulativeVarianceExplained": 0.9286320704,
    "Mask": "CSF",
    "Method": "aCompCor",
    "Retained": false,
    "SingularValue": 17.8275515067,
    "VarianceExplained": 0.0055269476
  },
  "dropped_5": {
    "CumulativeVarianceExplained": 0.5799091699,
    "Mask": "CSF",
    "Method": "aCompCor",
    "Retained": false,
    "SingularValue": 25.2758307804,
    "VarianceExplained": 0.0111099684
  },
  "dropped_50": {
    "CumulativeVarianceExplained": 0.9340541828,
    "Mask": "CSF",
    "Method": "aCompCor",
    "Retained": false,
    "SingularValue": 17.6576655383,
    "VarianceExplained": 0.0054221124
  },
  "dropped_51": {
    "CumulativeVarianceExplained": 0.9392080838,
    "Mask": "CSF",
    "Method": "aCompCor",
    "Retained": false,
    "SingularValue": 17.2153978377,
    "VarianceExplained": 0.005153901
  },
  "dropped_52": {
    "CumulativeVarianceExplained": 0.9443093469,
    "Mask": "CSF",
    "Method": "aCompCor",
    "Retained": false,
    "SingularValue": 17.127259927,
    "VarianceExplained": 0.0051012631
  },
  "dropped_53": {
    "CumulativeVarianceExplained": 0.9493217837,
    "Mask": "CSF",
    "Method": "aCompCor",
    "Retained": false,
    "SingularValue": 16.9774900218,
    "VarianceExplained": 0.0050124368
  },
  "dropped_54": {
    "CumulativeVarianceExplained": 0.9542923722,
    "Mask": "CSF",
    "Method": "aCompCor",
    "Retained": false,
    "SingularValue": 16.9064698464,
    "VarianceExplained": 0.0049705885
  },
  "dropped_55": {
    "CumulativeVarianceExplained": 0.9591594549,
    "Mask": "CSF",
    "Method": "aCompCor",
    "Retained": false,
    "SingularValue": 16.7295165287,
    "VarianceExplained": 0.0048670827
  },
  "dropped_56": {
    "CumulativeVarianceExplained": 0.9638020532,
    "Mask": "CSF",
    "Method": "aCompCor",
    "Retained": false,
    "SingularValue": 16.3391544789,
    "VarianceExplained": 0.0046425982
  },
  "dropped_57": {
    "CumulativeVarianceExplained": 0.9684009051,
    "Mask": "CSF",
    "Method": "aCompCor",
    "Retained": false,
    "SingularValue": 16.2619919215,
    "VarianceExplained": 0.0045988519
  },
  "dropped_58": {
    "CumulativeVarianceExplained": 0.9728391776,
    "Mask": "CSF",
    "Method": "aCompCor",
    "Retained": false,
    "SingularValue": 15.9755570051,
    "VarianceExplained": 0.0044382725
  },
  "dropped_59": {
    "CumulativeVarianceExplained": 0.9772318426,
    "Mask": "CSF",
    "Method": "aCompCor",
    "Retained": false,
    "SingularValue": 15.8932629268,
    "VarianceExplained": 0.004392665
  },
  "dropped_6": {
    "CumulativeVarianceExplained": 0.5907522876,
    "Mask": "CSF",
    "Method": "aCompCor",
    "Retained": false,
    "SingularValue": 24.9704353795,
    "VarianceExplained": 0.0108431177
  },
  "dropped_60": {
    "CumulativeVarianceExplained": 0.9814212527,
    "Mask": "CSF",
    "Method": "aCompCor",
    "Retained": false,
    "SingularValue": 15.5212062234,
    "VarianceExplained": 0.0041894102
  },
  "dropped_61": {
    "CumulativeVarianceExplained": 0.9855467346,
    "Mask": "CSF",
    "Method": "aCompCor",
    "Retained": false,
    "SingularValue": 15.4023279961,
    "VarianceExplained": 0.0041254818
  },
  "dropped_62": {
    "CumulativeVarianceExplained": 0.9895493894,
    "Mask": "CSF",
    "Method": "aCompCor",
    "Retained": false,
    "SingularValue": 15.1713105255,
    "VarianceExplained": 0.0040026548
  },
  "dropped_63": {
    "CumulativeVarianceExplained": 0.993146524,
    "Mask": "CSF",
    "Method": "aCompCor",
    "Retained": false,
    "SingularValue": 14.3822678012,
    "VarianceExplained": 0.0035971346
  },
  "dropped_64": {
    "CumulativeVarianceExplained": 0.9966972384,
    "Mask": "CSF",
    "Method": "aCompCor",
    "Retained": false,
    "SingularValue": 14.2891666365,
    "VarianceExplained": 0.0035507144
  },
  "dropped_65": {
    "CumulativeVarianceExplained": 1.0,
    "Mask": "CSF",
    "Method": "aCompCor",
    "Retained": false,
    "SingularValue": 13.7812191492,
    "VarianceExplained": 0.0033027616
  },
  "dropped_66": {
    "CumulativeVarianceExplained": 1.0,
    "Mask": "CSF",
    "Method": "aCompCor",
    "Retained": false,
    "SingularValue": 0.0,
    "VarianceExplained": 0.0
  },
  "dropped_67": {
    "CumulativeVarianceExplained": 1.0,
    "Mask": "CSF",
    "Method": "aCompCor",
    "Retained": false,
    "SingularValue": 0.0,
    "VarianceExplained": 0.0
  },
  "dropped_68": {
    "CumulativeVarianceExplained": 1.0,
    "Mask": "CSF",
    "Method": "aCompCor",
    "Retained": false,
    "SingularValue": 0.0,
    "VarianceExplained": 0.0
  },
  "dropped_69": {
    "CumulativeVarianceExplained": 0.5141905364,
    "Mask": "WM",
    "Method": "aCompCor",
    "Retained": false,
    "SingularValue": 85.8473174864,
    "VarianceExplained": 0.0104432531
  },
  "dropped_7": {
    "CumulativeVarianceExplained": 0.6014222408,
    "Mask": "CSF",
    "Method": "aCompCor",
    "Retained": false,
    "SingularValue": 24.7702439751,
    "VarianceExplained": 0.0106699532
  },
  "dropped_70": {
    "CumulativeVarianceExplained": 0.5245442103,
    "Mask": "WM",
    "Method": "aCompCor",
    "Retained": false,
    "SingularValue": 85.4783375647,
    "VarianceExplained": 0.0103536738
  },
  "dropped_71": {
    "CumulativeVarianceExplained": 0.5348929319,
    "Mask": "WM",
    "Method": "aCompCor",
    "Retained": false,
    "SingularValue": 85.4578931387,
    "VarianceExplained": 0.0103487217
  },
  "dropped_72": {
    "CumulativeVarianceExplained": 0.5451755987,
    "Mask": "WM",
    "Method": "aCompCor",
    "Retained": false,
    "SingularValue": 85.1847214514,
    "VarianceExplained": 0.0102826667
  },
  "dropped_73": {
    "CumulativeVarianceExplained": 0.5554039253,
    "Mask": "WM",
    "Method": "aCompCor",
    "Retained": false,
    "SingularValue": 84.9593384476,
    "VarianceExplained": 0.0102283266
  },
  "dropped_74": {
    "CumulativeVarianceExplained": 0.5656043051,
    "Mask": "WM",
    "Method": "aCompCor",
    "Retained": false,
    "SingularValue": 84.8431919581,
    "VarianceExplained": 0.0102003798
  },
  "dropped_75": {
    "CumulativeVarianceExplained": 0.57580077,
    "Mask": "WM",
    "Method": "aCompCor",
    "Retained": false,
    "SingularValue": 84.8269092689,
    "VarianceExplained": 0.010196465
  },
  "dropped_76": {
    "CumulativeVarianceExplained": 0.5859751182,
    "Mask": "WM",
    "Method": "aCompCor",
    "Retained": false,
    "SingularValue": 84.7348615824,
    "VarianceExplained": 0.0101743481
  },
  "dropped_77": {
    "CumulativeVarianceExplained": 0.5960587932,
    "Mask": "WM",
    "Method": "aCompCor",
    "Retained": false,
    "SingularValue": 84.3564409789,
    "VarianceExplained": 0.010083675
  },
  "dropped_78": {
    "CumulativeVarianceExplained": 0.6060913932,
    "Mask": "WM",
    "Method": "aCompCor",
    "Retained": false,
    "SingularValue": 84.1425322567,
    "VarianceExplained": 0.0100326001
  },
  "dropped_79": {
    "CumulativeVarianceExplained": 0.6160466872,
    "Mask": "WM",
    "Method": "aCompCor",
    "Retained": false,
    "SingularValue": 83.8177256021,
    "VarianceExplained": 0.009955294
  },
  "dropped_8": {
    "CumulativeVarianceExplained": 0.6120046825,
    "Mask": "CSF",
    "Method": "aCompCor",
    "Retained": false,
    "SingularValue": 24.6684561796,
    "VarianceExplained": 0.0105824417
  },
  "dropped_80": {
    "CumulativeVarianceExplained": 0.6259309491,
    "Mask": "WM",
    "Method": "aCompCor",
    "Retained": false,
    "SingularValue": 83.5181663011,
    "VarianceExplained": 0.0098842619
  },
  "dropped_81": {
    "CumulativeVarianceExplained": 0.6357975634,
    "Mask": "WM",
    "Method": "aCompCor",
    "Retained": false,
    "SingularValue": 83.4435750746,
    "VarianceExplained": 0.0098666143
  },
  "dropped_82": {
    "CumulativeVarianceExplained": 0.6456000138,
    "Mask": "WM",
    "Method": "aCompCor",
    "Retained": false,
    "SingularValue": 83.1718103713,
    "VarianceExplained": 0.0098024504
  },
  "dropped_83": {
    "CumulativeVarianceExplained": 0.6553896596,
    "Mask": "WM",
    "Method": "aCompCor",
    "Retained": false,
    "SingularValue": 83.1174705062,
    "VarianceExplained": 0.0097896458
  },
  "dropped_84": {
    "CumulativeVarianceExplained": 0.665144562,
    "Mask": "WM",
    "Method": "aCompCor",
    "Retained": false,
    "SingularValue": 82.9698472739,
    "VarianceExplained": 0.0097549023
  },
  "dropped_85": {
    "CumulativeVarianceExplained": 0.6748575365,
    "Mask": "WM",
    "Method": "aCompCor",
    "Retained": false,
    "SingularValue": 82.7913480294,
    "VarianceExplained": 0.0097129746
  },
  "dropped_86": {
    "CumulativeVarianceExplained": 0.6845527712,
    "Mask": "WM",
    "Method": "aCompCor",
    "Retained": false,
    "SingularValue": 82.7157080174,
    "VarianceExplained": 0.0096952347
  },
  "dropped_87": {
    "CumulativeVarianceExplained": 0.6942130207,
    "Mask": "WM",
    "Method": "aCompCor",
    "Retained": false,
    "SingularValue": 82.566333516,
    "VarianceExplained": 0.0096602495
  },
  "dropped_88": {
    "CumulativeVarianceExplained": 0.7038390317,
    "Mask": "WM",
    "Method": "aCompCor",
    "Retained": false,
    "SingularValue": 82.41988475,
    "VarianceExplained": 0.0096260109
  },
  "dropped_89": {
    "CumulativeVarianceExplained": 0.7134472545,
    "Mask": "WM",
    "Method": "aCompCor",
    "Retained": false,
    "SingularValue": 82.3436969483,
    "VarianceExplained": 0.0096082228
  },
  "dropped_9": {
    "CumulativeVarianceExplained": 0.6224338929,
    "Mask": "CSF",
    "Method": "aCompCor",
    "Retained": false,
    "SingularValue": 24.4892080647,
    "VarianceExplained": 0.0104292103
  },
  "dropped_90": {
    "CumulativeVarianceExplained": 0.7230281612,
    "Mask": "WM",
    "Method": "aCompCor",
    "Retained": false,
    "SingularValue": 82.2265621542,
    "VarianceExplained": 0.0095809067
  },
  "dropped_91": {
    "CumulativeVarianceExplained": 0.7325563096,
    "Mask": "WM",
    "Method": "aCompCor",
    "Retained": false,
    "SingularValue": 81.9998550901,
    "VarianceExplained": 0.0095281484
  },
  "dropped_92": {
    "CumulativeVarianceExplained": 0.7420447628,
    "Mask": "WM",
    "Method": "aCompCor",
    "Retained": false,
    "SingularValue": 81.8288666985,
    "VarianceExplained": 0.0094884531
  },
  "dropped_93": {
    "CumulativeVarianceExplained": 0.751457044,
    "Mask": "WM",
    "Method": "aCompCor",
    "Retained": false,
    "SingularValue": 81.4997497026,
    "VarianceExplained": 0.0094122812
  },
  "dropped_94": {
    "CumulativeVarianceExplained": 0.7608483714,
    "Mask": "WM",
    "Method": "aCompCor",
    "Retained": false,
    "SingularValue": 81.4089811229,
    "VarianceExplained": 0.0093913274
  },
  "dropped_95": {
    "CumulativeVarianceExplained": 0.7701794875,
    "Mask": "WM",
    "Method": "aCompCor",
    "Retained": false,
    "SingularValue": 81.14758977,
    "VarianceExplained": 0.0093311161
  },
  "dropped_96": {
    "CumulativeVarianceExplained": 0.7794912686,
    "Mask": "WM",
    "Method": "aCompCor",
    "Retained": false,
    "SingularValue": 81.0634729991,
    "VarianceExplained": 0.0093117811
  },
  "dropped_97": {
    "CumulativeVarianceExplained": 0.7887523223,
    "Mask": "WM",
    "Method": "aCompCor",
    "Retained": false,
    "SingularValue": 80.8423683101,
    "VarianceExplained": 0.0092610536
  },
  "dropped_98": {
    "CumulativeVarianceExplained": 0.7979511057,
    "Mask": "WM",
    "Method": "aCompCor",
    "Retained": false,
    "SingularValue": 80.5701228501,
    "VarianceExplained": 0.0091987835
  },
  "dropped_99": {
    "CumulativeVarianceExplained": 0.8071046707,
    "Mask": "WM",
    "Method": "aCompCor",
    "Retained": false,
    "SingularValue": 80.3718496216,
    "VarianceExplained": 0.009153565
  },
  "global_signal": {
    "Method": "Mean"
  },
  "t_comp_cor_00": {
    "CumulativeVarianceExplained": 0.2471814666,
    "Method": "tCompCor",
    "Retained": true,
    "SingularValue": 259.7359107127,
    "VarianceExplained": 0.2471814666
  },
  "t_comp_cor_01": {
    "CumulativeVarianceExplained": 0.4381725148,
    "Method": "tCompCor",
    "Retained": true,
    "SingularValue": 228.3129536422,
    "VarianceExplained": 0.1909910482
  },
  "t_comp_cor_02": {
    "CumulativeVarianceExplained": 0.5416974095,
    "Method": "tCompCor",
    "Retained": true,
    "SingularValue": 168.0917680096,
    "VarianceExplained": 0.1035248947
  },
  "tcompcor": {
    "Method": "Mean"
  },
  "white_matter": {
    "Method": "Mean"
  }
}