{
  "a_comp_cor_00": {
    "CumulativeVarianceExplained": 0.5616885665,
    "Mask": "CSF",
    "Method": "aCompCor",
    "Retained": true,
    "SingularValue": 27.0429013528,
    "VarianceExplained": 0.5616885665
  },
  "a_comp_cor_01": {
    "CumulativeVarianceExplained": 0.5114207405,
    "Mask": "WM",
    "Method": "aCompCor",
    "Retained": true,
    "SingularValue": 96.1932193936,
    "VarianceExplained": 0.5114207405
  },
  "a_comp_cor_02": {
    "CumulativeVarianceExplained": 0.5120947754,
    "Mask": "combined",
    "Method": "aCompCor",
    "Retained": true,
    "SingularValue": 97.1620665929,
    "VarianceExplained": 0.5120947754
  },
  "csf": {
    "Method": "Mean"
  },
  "csf_wm": {
    "Method": "Mean"
  },
  "dropped_0": {
    "CumulativeVarianceExplained": 1.0,
    "Mask": "CSF",
    "Method": "aCompCor",
    "Retained": false,
    "SingularValue": 23.8889406718,
    "VarianceExplained": 0.4383114335
  },
  "dropped_1": {
    "CumulativeVarianceExplained": 1.0,
    "Mask": "CSF",
    "Method": "aCompCor",
    "Retained": false,
    "SingularValue": 0.0,
    "VarianceExplained": 0.0
  },
  "dropped_2": {
    "CumulativeVarianceExplained": 1.0,
    "Mask": "WM",
    "Method": "aCompCor",
    "Retained": false,
    "SingularValue": 94.020553831,
    "VarianceExplained": 0.4885792595
  },
  "dropped_3": {
    "CumulativeVarianceExplained": 1.0,
    "Mask": "WM",
    "Method": "aCompCor",
    "Retained": false,
    "SingularValue": 0.0,
    "VarianceExplained": 0.0
  },
  "dropped_4": {
    "CumulativeVarianceExplained": 1.0,
    "Mask": "combined",
    "Method": "aCompCor",
    "Retained": false,
    "SingularValue": 94.8395108348,
    "VarianceExplained": 0.4879052246
  },
  "dropped_5": {
    "CumulativeVarianceExplained": 1.0,
    "Mask": "combined",
    "Method": "aCompCor",
    "Retained": false,
    "SingularValue": 0.0,
    "VarianceExplained": 0.0
  },
  "global_signal": {
    "Method": "Mean"
  },
  "t_comp_cor_00": {
    "CumulativeVarianceExplained": 0.5286665053,
    "Method": "tCompCor",
    "Retained": true,
    "SingularValue": 126.9212239311,
    "VarianceExplained": 0.5286665053
  },
  "tcompcor": {
    "Method": "Mean"
  },
  "white_matter": {
    "Method": "Mean"
  }
}